Metadata-Version: 2.1
Name: tool-spider-pro
Version: 1.0
Summary: This packges has tools from camera and video recorder.
Home-page: UNKNOWN
Author: krc0d3r
Author-email: kl3b7r@gmail.com
License: UNKNOWN
Keywords: camera,video,process
Platform: UNKNOWN
License-File: licence.txt
